pdf_maker/__init__.py
pdf_maker/_utils/__init__.py
pdf_maker/_utils/warns.py
pdf_maker/canvas/__init__.py
pdf_maker/canvas/area.py
pdf_maker/canvas/canvas.py
pdf_maker/canvas/plotarea.py
pdf_maker/constants/__init__.py
pdf_maker/constants/_global.py
pdf_maker/core/__init__.py
pdf_maker/core/base.py
pdf_maker/core/comps.py
pdf_maker/core/crf.py
pdf_maker/core/main.py
pdf_maker/core/objs.py
pdf_maker/resources/font/arial.ttf
pdf_maker/resources/font/arial.xml
pdf_maker/resources/font/calibri.ttf
pdf_maker/resources/font/calibri.xml
pdf_maker/resources/font/helvetica.ttf
pdf_maker/resources/font/helvetica.xml
pdf_maker/resources/font/micross.ttf
pdf_maker/resources/font/micross.xml
pdf_maker/resources/font/times.ttf
pdf_maker/resources/font/times.xml
pdf_maker/resources/subset/arial-subset.ttf
pdf_maker/resources/subset/calibri-subset.ttf
pdf_maker/resources/subset/helvetica-subset.ttf
pdf_maker/resources/subset/micross-subset.ttf
pdf_maker/resources/subset/times-subset.ttf
pdf_maker-0.0.56.dist-info/licenses/LICENSE
tests/__init__.py
tests/convert_ttf_to_xml.py
tests/pdf-parser.py
tests/test.py
pdf_maker-0.0.56.dist-info/METADATA
pdf_maker-0.0.56.dist-info/WHEEL
pdf_maker-0.0.56.dist-info/top_level.txt
pdf_maker-0.0.56.dist-info/RECORD
