Metadata-Version: 2.4
Name: pdf-maker
Version: 0.0.56
Summary: A module for creating PDF files
Home-page: https://github.com/wuyangchn/pdf-maker.git
Author: Yang Wu
Author-email: wuycug@hotmail.com
Classifier: Development Status :: 3 - Alpha
Classifier: Programming Language :: Python :: 3
Classifier: Operating System :: OS Independent
Requires-Python: >=3.5
License-File: LICENSE
Requires-Dist: numpy
Dynamic: author
Dynamic: author-email
Dynamic: classifier
Dynamic: description
Dynamic: description-content-type
Dynamic: home-page
Dynamic: license-file
Dynamic: requires-dist
Dynamic: requires-python
Dynamic: summary
